{
 "based_on": "posting_date",
 "chart_name": "Delivery Trends",
 "chart_type": "Sum",
 "color": "#4d4da8",
 "creation": "2020-12-29 14:37:50.258483",
 "docstatus": 0,
 "doctype": "Dashboard Chart",
 "document_type": "Delivery Note",
 "filters_json": "[[\"Delivery Note\",\"docstatus\",\"=\",1]]",
 "group_by_type": "Count",
 "idx": 0,
 "is_public": 1,
 "is_standard": 1,
 "last_synced_on": "2020-12-31 15:28:00.850803",
 "modified": "2021-01-02 16:06:16.879130",
 "modified_by": "Administrator",
 "module": "Finbyz Dashboard",
 "name": "Delivery Trends",
 "number_of_groups": 0,
 "owner": "Administrator",
 "time_interval": "Monthly",
 "timeseries": 1,
 "timespan": "Last Year",
 "type": "Bar",
 "use_report_chart": 0,
 "value_based_on": "base_net_total",
 "width": "Half",
 "y_axis": []
}